py_fh/__init__.py
py_fh-0.3.dist-info/LICENSE.txt
py_fh-0.3.dist-info/METADATA
py_fh-0.3.dist-info/WHEEL
py_fh-0.3.dist-info/top_level.txt
py_fh-0.3.dist-info/RECORD
