Metadata-Version: 2.2
Name: py_fh
Version: 0.3
Summary: test 🙂🤍
Author: Hasneen Ali
Classifier: Programming Language :: Python :: 3
Classifier: Operating System :: OS Independent
Classifier: License :: OSI Approved :: MIT License
License-File: LICENSE.txt
Dynamic: author
Dynamic: classifier
Dynamic: summary
